OrangePi_PidiPlugins
