Metadata-Version: 2.1
Name: OrangePi.PidiPlugins
Version: 1.1.1
Summary: Pidi plugins for display output using SPI LCDs on the OrangePi.
Home-page: https://github.com/sonocotta/pidi-plugins-python
Author: Andriy Malyshenko
Author-email: andriy@sonocotta.com
License: MIT
Classifier: Environment :: X11 Applications
Classifier: License :: OSI Approved :: MIT License
Classifier: Operating System :: POSIX :: Linux
Classifier: Programming Language :: Python :: 3.6
Requires-Python: >=2.7
